dapr/ext/workflow/__init__.py
dapr/ext/workflow/dapr_workflow_client.py
dapr/ext/workflow/dapr_workflow_context.py
dapr/ext/workflow/py.typed
dapr/ext/workflow/retry_policy.py
dapr/ext/workflow/util.py
dapr/ext/workflow/version.py
dapr/ext/workflow/workflow_activity_context.py
dapr/ext/workflow/workflow_context.py
dapr/ext/workflow/workflow_runtime.py
dapr/ext/workflow/workflow_state.py
dapr/ext/workflow/aio/__init__.py
dapr/ext/workflow/aio/dapr_workflow_client.py
dapr/ext/workflow/logger/__init__.py
dapr/ext/workflow/logger/logger.py
dapr/ext/workflow/logger/options.py
dapr_ext_workflow_dev-1.16.0.dev60.dist-info/licenses/LICENSE
dapr_ext_workflow_dev-1.16.0.dev60.dist-info/METADATA
dapr_ext_workflow_dev-1.16.0.dev60.dist-info/WHEEL
dapr_ext_workflow_dev-1.16.0.dev60.dist-info/top_level.txt
dapr_ext_workflow_dev-1.16.0.dev60.dist-info/RECORD
